{"decls":[{"kind":"export","names":["state.default_doc_v1"]},{"body":["bytes.lit","{\"session\":{\"user_id\":null,\"role\":\"technician\",\"branch_id\":\"branch_north\",\"team_id\":\"team_north_alpha\",\"token\":\"\",\"status\":\"idle\"},\"bootstrap\":{\"status\":\"idle\",\"source\":\"none\",\"last_loaded_at\":null,\"error\":null},\"ui\":{\"route\":\"today\",\"sidebar_open\":false,\"selected_work_order_id\":\"wo_001\",\"filter_status\":\"all\",\"branch_id\":\"branch_north\",\"team_id\":\"team_north_alpha\",\"last_action\":\"\"},\"entities\":{\"org\":{},\"branches\":{},\"teams\":{},\"users\":{},\"customers\":{},\"sites\":{},\"assets\":{},\"work_orders\":{},\"visits\":{},\"templates\":{}},\"indexes\":{\"work_orders_by_status\":{},\"work_orders_by_assignee\":{},\"assets_by_site\":{},\"sites_by_customer\":{}},\"sync\":{\"cursor\":null,\"pending_ops\":[],\"last_pull_at\":null,\"last_push_at\":null,\"status\":\"idle\",\"last_error\":null},\"settings\":{\"theme\":\"system\",\"density\":\"comfortable\",\"pinned_views\":[],\"dev_flags\":{}},\"diagnostics\":{\"app_version\":\"0.1.0\",\"target_kind\":\"web\",\"build_profile\":\"dev\"},\"summary\":{\"counts\":{\"branches\":0,\"teams\":0,\"technicians\":0,\"customers\":0,\"sites\":0,\"assets\":0,\"work_orders\":0},\"status_counts\":{},\"attention_work_orders\":[],\"dispatcher_focus\":[],\"manager_metrics\":{\"overdue\":0,\"blocked\":0,\"review\":0,\"completion_rate\":\"0%\"},\"technician_today\":{}}}"],"kind":"defn","name":"state.default_doc_v1","params":[],"result":"bytes"}],"imports":[],"kind":"module","module_id":"state","schema_version":"x07.x07ast@0.5.0"}
